Metadata-Version: 1.0
Name: mlops
Version: 0.1.0
Summary: ML-ops
Home-page: https://github.com/ornew/mlops
Author: Arata Furukawa
Author-email: info@ornew.net
License: UNKNOWN
Platform: UNKNOWN
